ContactPy-1.2.3.data/scripts/__init__.py
ContactPy-1.2.3.data/scripts/gmail.py
ContactPy-1.2.3.data/scripts/vcf.py
contacts/__init__.py
contacts/gmail.py
contacts/vcf.py
ContactPy-1.2.3.dist-info/LICENSE
ContactPy-1.2.3.dist-info/METADATA
ContactPy-1.2.3.dist-info/WHEEL
ContactPy-1.2.3.dist-info/top_level.txt
ContactPy-1.2.3.dist-info/RECORD
