Metadata-Version: 2.1
Name: ContactPy
Version: 1.2.3
Summary: Useful tools to work with Contacts in Python
Home-page: https://github.com/judah-b2/PyContacts
Author: Judah Beethoven
Author-email: masterofcoding360@gmail.com
License: MIT
Keywords: vcf,contacts,Contacts Python,gmail
Platform: UNKNOWN
